textfsmgen/__init__.py
textfsmgen/__main__.py
textfsmgen/application.py
textfsmgen/config.py
textfsmgen/core.py
textfsmgen/deps.py
textfsmgen/exceptions.py
textfsmgen/gp.py
textfsmgen/gpcategory.py
textfsmgen/gpcommon.py
textfsmgen/gpdiff.py
textfsmgen/gpiterative.py
textfsmgen/gptabular.py
textfsmgen/main.py
textfsmgen/verify.py
textfsmgen-0.3.1a1.dist-info/licenses/LICENSE
textfsmgen-0.3.1a1.dist-info/METADATA
textfsmgen-0.3.1a1.dist-info/WHEEL
textfsmgen-0.3.1a1.dist-info/entry_points.txt
textfsmgen-0.3.1a1.dist-info/top_level.txt
textfsmgen-0.3.1a1.dist-info/RECORD
