Metadata-Version: 2.4
Name: textfsmgen
Version: 0.3.1a1
Summary: TextFSM Generator simplifies template creation by converting plain English snippets into reusable parsing rules, standardizing workflows and enhancing collaboration across teams.
Home-page: https://github.com/Geeks-Trident-LLC/textfsmgen
Author: Tuyen Mathew Duong
Author-email: tuyen@geekstrident.com
Maintainer: Tuyen Mathew Duong
Maintainer-email: tuyen@geekstrident.com
License: BSD-3-Clause
Project-URL: Documentation, https://github.com/Geeks-Trident-LLC/textfsmgen/wiki
Project-URL: Source, https://github.com/Geeks-Trident-LLC/textfsmgen
Project-URL: Tracker, https://github.com/Geeks-Trident-LLC/textfsmgen/issues
Keywords: textfsm,textfsm generator,text parsing,automation,verification,validation,qa,robotframework,test script,test case,test plan,ai integration
Classifier: Development Status :: 3 - Alpha
Classifier: Natural Language :: English
Classifier: Intended Audience :: Developers
Classifier: Intended Audience :: Education
Classifier: Intended Audience :: End Users/Desktop
Classifier: Intended Audience :: Information Technology
Classifier: Intended Audience :: Manufacturing
Classifier: Intended Audience :: Other Audience
Classifier: Intended Audience :: Science/Research
Classifier: Operating System :: MacOS :: MacOS X
Classifier: Operating System :: POSIX :: Linux
Classifier: Operating System :: Microsoft :: Windows
Classifier: Programming Language :: Python
Classifier: Programming Language :: Python :: 3
Classifier: Programming Language :: Python :: 3.9
Classifier: Programming Language :: Python :: 3.10
Classifier: Programming Language :: Python :: 3.11
Classifier: Programming Language :: Python :: 3.12
Classifier: Topic :: Software Development :: Libraries :: Python Modules
Classifier: Topic :: Software Development :: Code Generators
Classifier: Topic :: Software Development :: Quality Assurance
Classifier: Topic :: Software Development :: Testing
Classifier: Topic :: Scientific/Engineering
Classifier: Topic :: Text Processing
Requires-Python: >=3.9
License-File: LICENSE
Requires-Dist: textfsm>=1.1.0
Requires-Dist: pyyaml>=6.0
Requires-Dist: genericlib
Requires-Dist: regexapp
Dynamic: author
Dynamic: author-email
Dynamic: classifier
Dynamic: description
Dynamic: description-content-type
Dynamic: home-page
Dynamic: keywords
Dynamic: license
Dynamic: license-file
Dynamic: maintainer
Dynamic: maintainer-email
Dynamic: project-url
Dynamic: requires-dist
Dynamic: requires-python
Dynamic: summary
